Metadata-Version: 2.1
Name: ffcv
Version: 1.0.2
Summary:  FFCV: Fast Forward Computer Vision 
Home-page: https://github.com/libffcv/ffcv
Author: MadryLab
Author-email: ffcv@mit.edu
License: UNKNOWN
Platform: UNKNOWN
